saas/__init__.py
saas/admin.py
saas/api_urls.py
saas/apps.py
saas/middleware.py
saas/models.py
saas/saas_permissions.py
saas/settings.py
saas/signals.py
saas/spectacular_schema.py
saas/test.py
saas/db/__init__.py
saas/db/cache.py
saas/db/defaults.py
saas/db/fields.py
saas/db/manager.py
saas/domain/__init__.py
saas/domain/_ready.py
saas/domain/admin.py
saas/domain/api_urls.py
saas/domain/apps.py
saas/domain/middleware.py
saas/domain/models.py
saas/domain/saas_permissions.py
saas/domain/serializers.py
saas/domain/settings.py
saas/domain/signals.py
saas/domain/spectacular_schema.py
saas/domain/types.py
saas/domain/endpoints/__init__.py
saas/domain/endpoints/domain.py
saas/domain/management/__init__.py
saas/domain/management/commands/__init__.py
saas/domain/management/commands/verify_domains.py
saas/domain/migrations/0001_initial.py
saas/domain/migrations/__init__.py
saas/domain/providers/__init__.py
saas/domain/providers/base.py
saas/domain/providers/cloudflare.py
saas/domain/providers/null.py
saas/domain/registry/__init__.py
saas/domain/registry/default_roles.py
saas/drf/__init__.py
saas/drf/apps.py
saas/drf/decorators.py
saas/drf/errors.py
saas/drf/filters.py
saas/drf/permissions.py
saas/drf/serializers.py
saas/drf/spectacular.py
saas/drf/spectacular_schema.py
saas/drf/types.py
saas/drf/views.py
saas/fixtures/test_data.yaml
saas/identity/__init__.py
saas/identity/_ready.py
saas/identity/admin.py
saas/identity/api_urls.py
saas/identity/apps.py
saas/identity/backends.py
saas/identity/gravatar.py
saas/identity/saas_permissions.py
saas/identity/settings.py
saas/identity/signals.py
saas/identity/urls.py
saas/identity/views.py
saas/identity/endpoints/__init__.py
saas/identity/endpoints/auth.py
saas/identity/endpoints/invitations.py
saas/identity/endpoints/password.py
saas/identity/endpoints/tenant.py
saas/identity/endpoints/user.py
saas/identity/endpoints/user_emails.py
saas/identity/endpoints/user_invitations.py
saas/identity/endpoints/user_tenants.py
django_saas-0.1.0.dist-info/METADATA
django_saas-0.1.0.dist-info/WHEEL
django_saas-0.1.0.dist-info/RECORD
