Metadata-Version: 2.4
Name: django-saas
Version: 0.1.0
Summary: The foundation for building a SaaS product with Django
Author-email: Hsiaoming Yang <me@lepture.com>
License: BSD-3-Clause
Classifier: Development Status :: 4 - Beta
Classifier: Environment :: Web Environment
Classifier: Framework :: Django
Classifier: Framework :: Django :: 5.0
Classifier: Framework :: Django :: 5.1
Classifier: Framework :: Django :: 5.2
Classifier: Framework :: Django :: 6.0
Classifier: Intended Audience :: Developers
Classifier: License :: OSI Approved :: BSD License
Classifier: Operating System :: OS Independent
Classifier: Programming Language :: Python
Classifier: Programming Language :: Python :: 3
Classifier: Programming Language :: Python :: 3.12
Classifier: Programming Language :: Python :: 3.13
Classifier: Programming Language :: Python :: 3.14
Classifier: Topic :: Internet :: WWW/HTTP
Requires-Python: >=3.12
Requires-Dist: css-inline
Requires-Dist: django
Requires-Dist: djangorestframework
Requires-Dist: joserfc
Requires-Dist: requests
